mpy_cross_v6-1.1.1.data/purelib/mpy_cross_v6/__init__.py
mpy_cross_v6-1.1.1.data/purelib/mpy_cross_v6/__main__.py
mpy_cross_v6-1.1.1.data/purelib/mpy_cross_v6/mpy-cross.exe
mpy_cross_v6-1.1.1.data/purelib/mpy_cross_v6/py.typed
mpy_cross_v6-1.1.1.dist-info/METADATA
mpy_cross_v6-1.1.1.dist-info/WHEEL
mpy_cross_v6-1.1.1.dist-info/entry_points.txt
mpy_cross_v6-1.1.1.dist-info/top_level.txt
mpy_cross_v6-1.1.1.dist-info/RECORD
